Iconlib/Iconlib.py
Iconlib/__init__.py
Iconlib/main (1).py
iconlib-0.4.dist-info/METADATA
iconlib-0.4.dist-info/WHEEL
iconlib-0.4.dist-info/entry_points.txt
iconlib-0.4.dist-info/top_level.txt
iconlib-0.4.dist-info/RECORD
