Metadata-Version: 2.2
Name: iconlib
Version: 0.4
Summary: A Python library for exploring the Constitution of India.
Home-page: https://github.com/Vikhram-S/Iconlib
Author: Vikhram S
Author-email: vikhrams@saveetha.ac.in
License: Apache License 2.0
Project-URL: Documentation, https://github.com/Vikhram-S/Iconlib/blob/main/README.md
Project-URL: Source, https://github.com/Vikhram-S/Iconlib
Project-URL: Issue Tracker, https://github.com/Vikhram-S/Iconlib/issues
Keywords: constitution india python library educational
Classifier: Development Status :: 4 - Beta
Classifier: Intended Audience :: Developers
Classifier: License :: OSI Approved :: Apache Software License
Classifier: Operating System :: OS Independent
Classifier: Programming Language :: Python :: 3.11
Classifier: Topic :: Software Development :: Libraries
Classifier: Topic :: Education
Classifier: Topic :: Utilities
Requires-Python: >=3.7
Provides-Extra: dev
Requires-Dist: pytest; extra == "dev"
Requires-Dist: flake8; extra == "dev"
Dynamic: author
Dynamic: author-email
Dynamic: classifier
Dynamic: description
Dynamic: description-content-type
Dynamic: home-page
Dynamic: keywords
Dynamic: license
Dynamic: project-url
Dynamic: provides-extra
Dynamic: requires-python
Dynamic: summary
